LICENSE
illuminate/__init__.py
illuminate/adapter/__init__.py
illuminate/adapter/adapter.py
illuminate/cli.py
illuminate/common/__init__.py
illuminate/common/project_definitions.py
illuminate/common/project_logging.py
illuminate/common/project_templates.py
illuminate/decorators/__init__.py
illuminate/decorators/cli.py
illuminate/decorators/logging.py
illuminate/exceptions/__init__.py
illuminate/exceptions/adapter.py
illuminate/exceptions/basic.py
illuminate/exceptions/exporter.py
illuminate/exceptions/manager.py
illuminate/exceptions/observation.py
illuminate/exceptions/observer.py
illuminate/exporter/__init__.py
illuminate/exporter/exporter.py
illuminate/exporter/influxdb.py
illuminate/exporter/sql.py
illuminate/interface/__init__.py
illuminate/interface/adapter.py
illuminate/interface/assistant.py
illuminate/interface/exporter.py
illuminate/interface/finding.py
illuminate/interface/manager.py
illuminate/interface/observation.py
illuminate/interface/observer.py
illuminate/manager/__init__.py
illuminate/manager/assistant.py
illuminate/manager/manager.py
illuminate/meta/__init__.py
illuminate/meta/type/__init__.py
illuminate/meta/type/result.py
illuminate/observation/__init__.py
illuminate/observation/file.py
illuminate/observation/http.py
illuminate/observation/observation.py
illuminate/observation/sql.py
illuminate/observer/__init__.py
illuminate/observer/finding.py
illuminate/observer/observer.py
illuminated-0.3.6.dist-info/LICENSE
illuminated-0.3.6.dist-info/METADATA
illuminated-0.3.6.dist-info/WHEEL
illuminated-0.3.6.dist-info/entry_points.txt
illuminated-0.3.6.dist-info/RECORD
