Metadata-Version: 2.1
Name: illuminated
Version: 0.3.6
Summary: Lightwieght ETL Framework
Home-page: https://github.com/nikolamilojica/illuminate
License: MIT
Keywords: ETL,Scraping
Author: Nikola Milojica
Author-email: nikola.milojica@protonmail.com
Requires-Python: >=3.9,<3.13
Classifier: Environment :: Console
Classifier: Intended Audience :: Developers
Classifier: License :: OSI Approved :: MIT License
Classifier: Programming Language :: Python :: 3
Classifier: Programming Language :: Python :: 3.9
Classifier: Programming Language :: Python :: 3.10
Classifier: Programming Language :: Python :: 3.11
Classifier: Programming Language :: Python :: 3.12
Requires-Dist: SQLAlchemy[asyncio] (>=2.0.31,<3.0.0)
Requires-Dist: aiofile (>=3.8.1,<4.0.0)
Requires-Dist: aioinflux (>=0.9.0,<0.10.0)
Requires-Dist: alembic (==1.13.2)
Requires-Dist: asyncmy (>=0.2.5,<0.3.0)
Requires-Dist: asyncpg (==0.29.0)
Requires-Dist: click (>=8.1.2,<9.0.0)
Requires-Dist: loguru (>=0.6.0,<0.7.0)
Requires-Dist: numpy (==1.26.4)
Requires-Dist: pandas (>=2.0.3,<3.0.0)
Requires-Dist: psycopg2 (==2.9.9)
Requires-Dist: tornado (==6.4.2)
Project-URL: Documentation, https://nikolamilojica.github.io/illuminate/
Project-URL: Repository, https://github.com/nikolamilojica/illuminate
